liboml/__init__.py
liboml/util.py
liboml/deep/__init__.py
liboml/deep/mlp.py
liboml/deep/odl.py
liboml/deep/odlae.py
liboml/kernel/__init__.py
liboml/kernel/ogd.py
liboml/kernel/perceptron.py
liboml/kernel/svm.py
liboml/linear/__init__.py
liboml/linear/ogd.py
liboml/linear/pa.py
liboml/linear/perceptron.py
liboml-0.0.2.dist-info/METADATA
liboml-0.0.2.dist-info/WHEEL
liboml-0.0.2.dist-info/top_level.txt
liboml-0.0.2.dist-info/RECORD
