Metadata-Version: 2.1
Name: liboml
Version: 0.0.2
Summary: Library For Online Machine Learning
Home-page: https://github.com/Kaslanarian/LIBOML
Author: Welt Xing
Author-email: xingcy@smail.nju.edu.cn
Maintainer: Welt Xing
Maintainer-email: xingcy@smail.nju.edu.cn
License: MIT License
Requires-Dist: numpy
Requires-Dist: scikit-learn
Requires-Dist: torch
